pygems/cli/__init__.py
pygems/core/__init__.py
pygems/core/conftest.py
pygems/core/namespace.py
pygems/core/plugin.py
pygems/core/shortcuts.py
pygems/core/timer.py
pygems/core/tests/__init__.py
pygems/core/tests/test_shortcuts.py
pygems/core/tests/test_timer.py
pygems/demo/__init__.py
pygems/demo/helloworld.py
pygems-0.2.0.dist-info/LICENSE
pygems-0.2.0.dist-info/METADATA
pygems-0.2.0.dist-info/WHEEL
pygems-0.2.0.dist-info/entry_points.txt
pygems-0.2.0.dist-info/top_level.txt
pygems-0.2.0.dist-info/RECORD
